MANIFEST.in
setup.py
docs/HISTORY.txt
src/dolmen/__init__.py
src/dolmen.app.layout.egg-info/PKG-INFO
src/dolmen.app.layout.egg-info/SOURCES.txt
src/dolmen.app.layout.egg-info/dependency_links.txt
src/dolmen.app.layout.egg-info/namespace_packages.txt
src/dolmen.app.layout.egg-info/not-zip-safe
src/dolmen.app.layout.egg-info/requires.txt
src/dolmen.app.layout.egg-info/top_level.txt
src/dolmen/app/__init__.py
src/dolmen/app/layout/README.txt
src/dolmen/app/layout/__init__.py
src/dolmen/app/layout/configure.zcml
src/dolmen/app/layout/errors.py
src/dolmen/app/layout/interfaces.py
src/dolmen/app/layout/master.py
src/dolmen/app/layout/menus.py
src/dolmen/app/layout/models.py
src/dolmen/app/layout/skin.py
src/dolmen/app/layout/skin.zcml
src/dolmen/app/layout/viewlets.py
src/dolmen/app/layout/locales/fr/LC_MESSAGES/dolmen.app.layout.po
src/dolmen/app/layout/templates/master.pt
src/dolmen/app/layout/templates/notfound.pt
src/dolmen/app/layout/tests/__init__.py
src/dolmen/app/layout/tests/ftesting.zcml
src/dolmen/app/layout/tests/test_package.py
src/dolmen/app/layout/viewlets_templates/flashmessages.pt
src/dolmen/app/layout/viewlets_templates/menu.pt