Metadata-Version: 1.1
Name: dolmen.app.layout
Version: 1.0
Summary: Layout and page models for Dolmen applications
Home-page: http://gitweb.dolmen-project.org/
Author: Souheil Chelfouh
Author-email: trollfot@gmail.com
License: GPL
Keywords: Grok Zope3 CMS Dolmen
Platform: Any
Classifier: Environment :: Web Environment
Classifier: Framework :: Zope3
Classifier: License :: OSI Approved :: GNU General Public License (GPL)
Classifier: Operating System :: OS Independent
Classifier: Programming Language :: Python
